autorepr.py
autorepr-0.3.0.dist-info/DESCRIPTION.rst
autorepr-0.3.0.dist-info/METADATA
autorepr-0.3.0.dist-info/metadata.json
autorepr-0.3.0.dist-info/RECORD
autorepr-0.3.0.dist-info/top_level.txt
autorepr-0.3.0.dist-info/WHEEL
